build/lib/build/lib/build/lib/build/lib/build/lib/build/lib/build/lib/build/lib/xicam/SAXS/SAXSGUIPlugin.py
build/lib/build/lib/build/lib/build/lib/build/lib/build/lib/build/lib/build/lib/xicam/SAXS/__init__.py
build/lib/build/lib/build/lib/build/lib/build/lib/build/lib/build/lib/build/lib/xicam/SAXS/_version.py
build/lib/build/lib/build/lib/build/lib/build/lib/build/lib/build/lib/build/lib/xicam/SAXS/calibration/CalibrationPanel.py
build/lib/build/lib/build/lib/build/lib/build/lib/build/lib/build/lib/build/lib/xicam/SAXS/calibration/__init__.py
build/lib/build/lib/build/lib/build/lib/build/lib/build/lib/build/lib/build/lib/xicam/SAXS/calibration/cwt.py
build/lib/build/lib/build/lib/build/lib/build/lib/build/lib/build/lib/build/lib/xicam/SAXS/calibration/fourierautocorrelation.py
build/lib/build/lib/build/lib/build/lib/build/lib/build/lib/build/lib/build/lib/xicam/SAXS/calibration/naivesdd.py
build/lib/build/lib/build/lib/build/lib/build/lib/build/lib/build/lib/build/lib/xicam/SAXS/calibration/simulatecalibrant.py
build/lib/build/lib/build/lib/build/lib/build/lib/build/lib/build/lib/build/lib/xicam/SAXS/calibration/workflows.py
build/lib/build/lib/build/lib/build/lib/build/lib/build/lib/build/lib/build/lib/xicam/SAXS/canvases/__init__.py
build/lib/build/lib/build/lib/build/lib/build/lib/build/lib/build/lib/build/lib/xicam/SAXS/data/__init__.py
build/lib/build/lib/build/lib/build/lib/build/lib/build/lib/build/lib/build/lib/xicam/SAXS/detectors/__init__.py
build/lib/build/lib/build/lib/build/lib/build/lib/build/lib/build/lib/build/lib/xicam/SAXS/formats/APSXPCS.py
build/lib/build/lib/build/lib/build/lib/build/lib/build/lib/build/lib/build/lib/xicam/SAXS/formats/EDFPlugin.py
build/lib/build/lib/build/lib/build/lib/build/lib/build/lib/build/lib/build/lib/xicam/SAXS/formats/TIFPlugin.py
build/lib/build/lib/build/lib/build/lib/build/lib/build/lib/build/lib/build/lib/xicam/SAXS/formats/__init__.py
xicam.SAXS-2.2.2.dist-info/LICENSE.md
xicam.SAXS-2.2.2.dist-info/METADATA
xicam.SAXS-2.2.2.dist-info/WHEEL
xicam.SAXS-2.2.2.dist-info/entry_points.txt
xicam.SAXS-2.2.2.dist-info/top_level.txt
xicam.SAXS-2.2.2.dist-info/RECORD
