Metadata-Version: 2.1
Name: xicam.SAXS
Version: 2.2.2
Summary: SAXS GUI Interface
Home-page: https://github.com/ronpandolfi/Xi-cam
Author: Ronald J Pandolfi
Author-email: ronpandolfi@lbl.gov
License: BSD
Keywords: synchrotron analysis x-ray scattering tomography
Classifier: Development Status :: 4 - Beta
Classifier: Intended Audience :: Science/Research
Classifier: Topic :: Scientific/Engineering :: Physics
Classifier: License :: OSI Approved :: BSD License
Classifier: Programming Language :: Python :: 3.6
License-File: LICENSE.md
Requires-Dist: xicam
Requires-Dist: numpy
Requires-Dist: qtpy
Requires-Dist: pyFAI (<0.21)
Requires-Dist: scipy
Requires-Dist: dill
Requires-Dist: scikit-image
Requires-Dist: databroker (>=1.0.0b1)
Requires-Dist: scikit-beam
Requires-Dist: camsaxs
Requires-Dist: numba
Provides-Extra: tests
Requires-Dist: pytest ; extra == 'tests'
Requires-Dist: coverage ; extra == 'tests'
